setup.py
bpformation/__init__.py
bpformation/api.py
bpformation/blueprint.py
bpformation/cli.py
bpformation/defaults.py
bpformation/output.py
bpformation/package.py
bpformation/queue.py
bpformation/shell.py
bpformation/terminal_size.py
bpformation/web.py
bpformation.egg-info/PKG-INFO
bpformation.egg-info/SOURCES.txt
bpformation.egg-info/dependency_links.txt
bpformation.egg-info/entry_points.txt
bpformation.egg-info/pbr.json
bpformation.egg-info/requires.txt
bpformation.egg-info/top_level.txt