Metadata-Version: 1.0
Name: bpformation
Version: 0.20
Summary: Blueprint Formation CLI
Home-page: https://github.com/CenturyLinkCloud/bp-formation
Author: Keith Resar
Author-email: Keith.Resar@CenturyLinkCloud.com
License: UNKNOWN
Keywords: CenturyLink Cloud Blueprint CLI
Platform: UNKNOWN
